MANIFEST.in
setup.py
./swdclient.egg-info/PKG-INFO
./swdclient.egg-info/SOURCES.txt
./swdclient.egg-info/dependency_links.txt
./swdclient.egg-info/requires.txt
./swdclient.egg-info/top_level.txt
swdclient/__init__.py
swdclient/adapter.py
swdclient/libswd.so
swdclient/server.proto
swdclient/server_pb2.py
swdclient/server_pb2.pyc
swdclient/setup.py
swdclient/swdclient.c
swdclient/swdclient.py
swdclient/swdclient.pyc
swdclient/test.py
swdclient.egg-info/PKG-INFO
swdclient.egg-info/SOURCES.txt
swdclient.egg-info/dependency_links.txt
swdclient.egg-info/requires.txt
swdclient.egg-info/top_level.txt
swdclient/__pycache__/__init__.cpython-35.pyc
swdclient/__pycache__/server_pb2.cpython-35.pyc
swdclient/__pycache__/swdclient.cpython-35.pyc