Metadata-Version: 1.0
Name: swdclient
Version: 0.3.5
Summary: SafeWorking Drive Client SDK
Home-page: UNKNOWN
Author: yangguang
Author-email: yangguang@iscas.ac.cn
License: MulanPSL
Keywords: pip,iscas,auto
Platform: linux
